pyvhl/mirror_clients.py
pyvhl/model/__init__.py
pyvhl/model/_model.py
pyvhl/pyVHL.code-workspace
pyvhl/pyvhl.py
pyvhl/scratch.py
pyvhl/test.mp4
pyvhl-0.1.5.4.dist-info/METADATA
pyvhl-0.1.5.4.dist-info/WHEEL
pyvhl-0.1.5.4.dist-info/RECORD
