Metadata-Version: 2.1
Name: pyVHL
Version: 0.1.5.4
Summary: 
Author: problemxl
Author-email: email@github.com
Requires-Python: >=3.10,<4.0
Classifier: Programming Language :: Python :: 3
Classifier: Programming Language :: Python :: 3.10
Classifier: Programming Language :: Python :: 3.11
Classifier: Programming Language :: Python :: 3.12
Requires-Dist: aiohttp (>=3.9.5,<4.0.0)
Requires-Dist: beautifulsoup4
Requires-Dist: httpx (>=0.27.0,<0.28.0)
Requires-Dist: loguru
Requires-Dist: pydantic
Requires-Dist: requests
Requires-Dist: requests-toolbelt
Requires-Dist: retry
Requires-Dist: youtube-dl
